Metadata-Version: 2.1
Name: tongsuopy
Version: 1.0.1
Summary: Tongsuo Python SDK
Home-page: https://github.com/Tongsuo-Project/tongsuo-python-sdk
Author: Tongsuo Project Authors
Author-email: tongsuo-dev@tongsuo.net
License: Apache-2.0
Project-URL: Documentation, https://www.yuque.com/tsdoc/ts
Project-URL: Source, https://github.com/Tongsuo-Project/tongsuo-python-sdk
Project-URL: Issues, https://github.com/Tongsuo-Project/tongsuo-python-sdk/issues
Platform: UNKNOWN
Classifier: Development Status :: 5 - Production/Stable
Classifier: Intended Audience :: Developers
Classifier: License :: OSI Approved :: Apache Software License
Classifier: Natural Language :: English
Classifier: Operating System :: MacOS :: MacOS X
Classifier: Operating System :: POSIX
Classifier: Operating System :: POSIX :: BSD
Classifier: Operating System :: POSIX :: Linux
Classifier: Operating System :: Microsoft :: Windows
Classifier: Programming Language :: Python
Classifier: Programming Language :: Python :: 3
Classifier: Programming Language :: Python :: 3 :: Only
Classifier: Programming Language :: Python :: 3.6
Classifier: Programming Language :: Python :: 3.7
Classifier: Programming Language :: Python :: 3.8
Classifier: Programming Language :: Python :: 3.9
Classifier: Programming Language :: Python :: 3.10
Classifier: Programming Language :: Python :: 3.11
Classifier: Programming Language :: Python :: Implementation :: CPython
Classifier: Programming Language :: Python :: Implementation :: PyPy
Classifier: Topic :: Security :: Cryptography
Requires-Python: >=3.6
License-File: LICENSE
Requires-Dist: cffi (>=1.12)
Provides-Extra: pep8test
Requires-Dist: black ; extra == 'pep8test'
Requires-Dist: flake8 ; extra == 'pep8test'
Requires-Dist: flake8-import-order ; extra == 'pep8test'
Requires-Dist: pep8-naming ; extra == 'pep8test'
Provides-Extra: test
Requires-Dist: pytest (>=6.2.0) ; extra == 'test'
Requires-Dist: pytest-benchmark ; extra == 'test'
Requires-Dist: pytest-cov ; extra == 'test'
Requires-Dist: pytest-subtests ; extra == 'test'
Requires-Dist: pytest-xdist ; extra == 'test'
